__init__.py
main.py
cq_gears/__init__.py
cq_gears/bevel_gear.py
cq_gears/crossed_helical_gear.py
cq_gears/rack_gear.py
cq_gears/ring_gear.py
cq_gears/spur_gear.py
cq_gears/utils.py
cq_gears/worm_gear.py
cq_warehouse/__init__.py
cq_warehouse/bearing.py
cq_warehouse/chain.py
cq_warehouse/drafting.py
cq_warehouse/extensions.py
cq_warehouse/extensions_doc.py
cq_warehouse/fastener.py
cq_warehouse/sprocket.py
cq_warehouse/thread.py
creo_mcp-0.1.6.dist-info/METADATA
creo_mcp-0.1.6.dist-info/WHEEL
creo_mcp-0.1.6.dist-info/entry_points.txt
creo_mcp-0.1.6.dist-info/top_level.txt
creo_mcp-0.1.6.dist-info/RECORD
