Metadata-Version: 2.4
Name: creo-mcp
Version: 0.1.6
Summary: An MCP server with tools for CAD interaction and knowledge base retrieval.
Author-email: yangkunyi <colibri8n24@gmail.com>
License: MIT
Project-URL: Homepage, https://github.com/yangkunyi/creo-mcp
Project-URL: Repository, https://github.com/yangkunyi/creo-mcp
Keywords: mcp,cad,creo,cadquery,agent
Classifier: Development Status :: 3 - Alpha
Classifier: Programming Language :: Python :: 3
Classifier: License :: OSI Approved :: MIT License
Classifier: Operating System :: OS Independent
Requires-Python: >=3.12
Requires-Dist: cadquery>=2.5.2
Requires-Dist: creopyson>=0.7.7
Requires-Dist: httpx>=0.28.1
Requires-Dist: mcp[cli]>=1.11.0
Requires-Dist: openai>=1.95.1
Requires-Dist: build>=1.2.2.post1
Requires-Dist: twine>=6.1.0
